{
	"name": "enemyEngineFX",
	"plugin-id": "Sprite",
	"sid": 474589095986065,
	"isGlobal": false,
	"instanceVariables": [],
	"behaviorTypes": [
		{
			"behaviorId": "Tween",
			"name": "Tween",
			"sid": 885307557120721
		}
	],
	"effectTypes": [],
	"animations": {
		"items": [
			{
				"frames": [
					{
						"width": 102,
						"height": 112,
						"originX": 0.5,
						"originY": 0.5,
						"originalSource": "",
						"exportFormat": "lossless",
						"exportQuality": 0.8,
						"imageSpriteId": 8635824,
						"collisionPoly": {
							"points": [
								1,
								0,
								1,
								1,
								0,
								1,
								0,
								0
							]
						},
						"useCollisionPoly": true,
						"duration": 1
					},
					{
						"width": 102,
						"height": 112,
						"originX": 0.5,
						"originY": 0.5,
						"originalSource": "",
						"exportFormat": "lossless",
						"exportQuality": 0.8,
						"imageSpriteId": 73186,
						"collisionPoly": {
							"points": [
								1,
								0,
								1,
								1,
								0,
								1,
								0,
								0
							]
						},
						"useCollisionPoly": true,
						"duration": 1
					},
					{
						"width": 102,
						"height": 112,
						"originX": 0.5,
						"originY": 0.5,
						"originalSource": "",
						"exportFormat": "lossless",
						"exportQuality": 0.8,
						"imageSpriteId": 97918,
						"collisionPoly": {
							"points": [
								1,
								0,
								1,
								1,
								0,
								1,
								0,
								0
							]
						},
						"useCollisionPoly": true,
						"duration": 1
					},
					{
						"width": 102,
						"height": 112,
						"originX": 0.5,
						"originY": 0.5,
						"originalSource": "",
						"exportFormat": "lossless",
						"exportQuality": 0.8,
						"imageSpriteId": 2577879,
						"collisionPoly": {
							"points": [
								1,
								0,
								1,
								1,
								0,
								1,
								0,
								0
							]
						},
						"useCollisionPoly": true,
						"duration": 1
					},
					{
						"width": 102,
						"height": 112,
						"originX": 0.5,
						"originY": 0.5,
						"originalSource": "",
						"exportFormat": "lossless",
						"exportQuality": 0.8,
						"imageSpriteId": 7246649,
						"collisionPoly": {
							"points": [
								1,
								0,
								1,
								1,
								0,
								1,
								0,
								0
							]
						},
						"useCollisionPoly": true,
						"duration": 1
					},
					{
						"width": 102,
						"height": 112,
						"originX": 0.5,
						"originY": 0.5,
						"originalSource": "",
						"exportFormat": "lossless",
						"exportQuality": 0.8,
						"imageSpriteId": 1811938,
						"collisionPoly": {
							"points": [
								1,
								0,
								1,
								1,
								0,
								1,
								0,
								0
							]
						},
						"useCollisionPoly": true,
						"duration": 1
					},
					{
						"width": 102,
						"height": 112,
						"originX": 0.5,
						"originY": 0.5,
						"originalSource": "",
						"exportFormat": "lossless",
						"exportQuality": 0.8,
						"imageSpriteId": 3453182,
						"collisionPoly": {
							"points": [
								1,
								0,
								1,
								1,
								0,
								1,
								0,
								0
							]
						},
						"useCollisionPoly": true,
						"duration": 1
					},
					{
						"width": 102,
						"height": 112,
						"originX": 0.5,
						"originY": 0.5,
						"originalSource": "",
						"exportFormat": "lossless",
						"exportQuality": 0.8,
						"imageSpriteId": 7726428,
						"collisionPoly": {
							"points": [
								1,
								0,
								1,
								1,
								0,
								1,
								0,
								0
							]
						},
						"useCollisionPoly": true,
						"duration": 1
					}
				],
				"sid": 376252602395507,
				"name": "0",
				"isLooping": true,
				"isPingPong": false,
				"repeatCount": 1,
				"repeatTo": 0,
				"speed": 24
			},
			{
				"frames": [
					{
						"width": 102,
						"height": 112,
						"originX": 0.5,
						"originY": 0.5,
						"originalSource": "",
						"exportFormat": "lossless",
						"exportQuality": 0.8,
						"imageSpriteId": 8465912,
						"collisionPoly": {
							"points": [
								1,
								0,
								1,
								1,
								0,
								1,
								0,
								0
							]
						},
						"useCollisionPoly": true,
						"duration": 1
					},
					{
						"width": 102,
						"height": 112,
						"originX": 0.5,
						"originY": 0.5,
						"originalSource": "",
						"exportFormat": "lossless",
						"exportQuality": 0.8,
						"imageSpriteId": 5606644,
						"collisionPoly": {
							"points": [
								1,
								0,
								1,
								1,
								0,
								1,
								0,
								0
							]
						},
						"useCollisionPoly": true,
						"duration": 1
					},
					{
						"width": 102,
						"height": 112,
						"originX": 0.5,
						"originY": 0.5,
						"originalSource": "",
						"exportFormat": "lossless",
						"exportQuality": 0.8,
						"imageSpriteId": 3737055,
						"collisionPoly": {
							"points": [
								1,
								0,
								1,
								1,
								0,
								1,
								0,
								0
							]
						},
						"useCollisionPoly": true,
						"duration": 1
					},
					{
						"width": 102,
						"height": 112,
						"originX": 0.5,
						"originY": 0.5,
						"originalSource": "",
						"exportFormat": "lossless",
						"exportQuality": 0.8,
						"imageSpriteId": 5637891,
						"collisionPoly": {
							"points": [
								1,
								0,
								1,
								1,
								0,
								1,
								0,
								0
							]
						},
						"useCollisionPoly": true,
						"duration": 1
					},
					{
						"width": 102,
						"height": 112,
						"originX": 0.5,
						"originY": 0.5,
						"originalSource": "",
						"exportFormat": "lossless",
						"exportQuality": 0.8,
						"imageSpriteId": 2023987,
						"collisionPoly": {
							"points": [
								1,
								0,
								1,
								1,
								0,
								1,
								0,
								0
							]
						},
						"useCollisionPoly": true,
						"duration": 1
					},
					{
						"width": 102,
						"height": 112,
						"originX": 0.5,
						"originY": 0.5,
						"originalSource": "",
						"exportFormat": "lossless",
						"exportQuality": 0.8,
						"imageSpriteId": 7938036,
						"collisionPoly": {
							"points": [
								1,
								0,
								1,
								1,
								0,
								1,
								0,
								0
							]
						},
						"useCollisionPoly": true,
						"duration": 1
					},
					{
						"width": 102,
						"height": 112,
						"originX": 0.5,
						"originY": 0.5,
						"originalSource": "",
						"exportFormat": "lossless",
						"exportQuality": 0.8,
						"imageSpriteId": 3716322,
						"collisionPoly": {
							"points": [
								1,
								0,
								1,
								1,
								0,
								1,
								0,
								0
							]
						},
						"useCollisionPoly": true,
						"duration": 1
					},
					{
						"width": 102,
						"height": 112,
						"originX": 0.5,
						"originY": 0.5,
						"originalSource": "",
						"exportFormat": "lossless",
						"exportQuality": 0.8,
						"imageSpriteId": 7448599,
						"collisionPoly": {
							"points": [
								1,
								0,
								1,
								1,
								0,
								1,
								0,
								0
							]
						},
						"useCollisionPoly": true,
						"duration": 1
					}
				],
				"sid": 972439542014103,
				"name": "1",
				"isLooping": true,
				"isPingPong": false,
				"repeatCount": 1,
				"repeatTo": 0,
				"speed": 24
			},
			{
				"frames": [
					{
						"width": 102,
						"height": 112,
						"originX": 0.5,
						"originY": 0.5,
						"originalSource": "",
						"exportFormat": "lossless",
						"exportQuality": 0.8,
						"imageSpriteId": 8085433,
						"collisionPoly": {
							"points": [
								1,
								0,
								1,
								1,
								0,
								1,
								0,
								0
							]
						},
						"useCollisionPoly": true,
						"duration": 1
					},
					{
						"width": 102,
						"height": 112,
						"originX": 0.5,
						"originY": 0.5,
						"originalSource": "",
						"exportFormat": "lossless",
						"exportQuality": 0.8,
						"imageSpriteId": 3723336,
						"collisionPoly": {
							"points": [
								1,
								0,
								1,
								1,
								0,
								1,
								0,
								0
							]
						},
						"useCollisionPoly": true,
						"duration": 1
					},
					{
						"width": 102,
						"height": 112,
						"originX": 0.5,
						"originY": 0.5,
						"originalSource": "",
						"exportFormat": "lossless",
						"exportQuality": 0.8,
						"imageSpriteId": 939465,
						"collisionPoly": {
							"points": [
								1,
								0,
								1,
								1,
								0,
								1,
								0,
								0
							]
						},
						"useCollisionPoly": true,
						"duration": 1
					},
					{
						"width": 102,
						"height": 112,
						"originX": 0.5,
						"originY": 0.5,
						"originalSource": "",
						"exportFormat": "lossless",
						"exportQuality": 0.8,
						"imageSpriteId": 3535814,
						"collisionPoly": {
							"points": [
								1,
								0,
								1,
								1,
								0,
								1,
								0,
								0
							]
						},
						"useCollisionPoly": true,
						"duration": 1
					},
					{
						"width": 102,
						"height": 112,
						"originX": 0.5,
						"originY": 0.5,
						"originalSource": "",
						"exportFormat": "lossless",
						"exportQuality": 0.8,
						"imageSpriteId": 7244271,
						"collisionPoly": {
							"points": [
								1,
								0,
								1,
								1,
								0,
								1,
								0,
								0
							]
						},
						"useCollisionPoly": true,
						"duration": 1
					},
					{
						"width": 102,
						"height": 112,
						"originX": 0.5,
						"originY": 0.5,
						"originalSource": "",
						"exportFormat": "lossless",
						"exportQuality": 0.8,
						"imageSpriteId": 8450721,
						"collisionPoly": {
							"points": [
								1,
								0,
								1,
								1,
								0,
								1,
								0,
								0
							]
						},
						"useCollisionPoly": true,
						"duration": 1
					},
					{
						"width": 102,
						"height": 112,
						"originX": 0.5,
						"originY": 0.5,
						"originalSource": "",
						"exportFormat": "lossless",
						"exportQuality": 0.8,
						"imageSpriteId": 5955210,
						"collisionPoly": {
							"points": [
								1,
								0,
								1,
								1,
								0,
								1,
								0,
								0
							]
						},
						"useCollisionPoly": true,
						"duration": 1
					},
					{
						"width": 102,
						"height": 112,
						"originX": 0.5,
						"originY": 0.5,
						"originalSource": "",
						"exportFormat": "lossless",
						"exportQuality": 0.8,
						"imageSpriteId": 5490489,
						"collisionPoly": {
							"points": [
								1,
								0,
								1,
								1,
								0,
								1,
								0,
								0
							]
						},
						"useCollisionPoly": true,
						"duration": 1
					}
				],
				"sid": 385194880027200,
				"name": "2",
				"isLooping": true,
				"isPingPong": false,
				"repeatCount": 1,
				"repeatTo": 0,
				"speed": 24
			},
			{
				"frames": [
					{
						"width": 102,
						"height": 112,
						"originX": 0.5,
						"originY": 0.5,
						"originalSource": "",
						"exportFormat": "lossless",
						"exportQuality": 0.8,
						"imageSpriteId": 3281596,
						"collisionPoly": {
							"points": [
								1,
								0,
								1,
								1,
								0,
								1,
								0,
								0
							]
						},
						"useCollisionPoly": true,
						"duration": 1
					},
					{
						"width": 102,
						"height": 112,
						"originX": 0.5,
						"originY": 0.5,
						"originalSource": "",
						"exportFormat": "lossless",
						"exportQuality": 0.8,
						"imageSpriteId": 414354,
						"collisionPoly": {
							"points": [
								1,
								0,
								1,
								1,
								0,
								1,
								0,
								0
							]
						},
						"useCollisionPoly": true,
						"duration": 1
					},
					{
						"width": 102,
						"height": 112,
						"originX": 0.5,
						"originY": 0.5,
						"originalSource": "",
						"exportFormat": "lossless",
						"exportQuality": 0.8,
						"imageSpriteId": 523409,
						"collisionPoly": {
							"points": [
								1,
								0,
								1,
								1,
								0,
								1,
								0,
								0
							]
						},
						"useCollisionPoly": true,
						"duration": 1
					},
					{
						"width": 102,
						"height": 112,
						"originX": 0.5,
						"originY": 0.5,
						"originalSource": "",
						"exportFormat": "lossless",
						"exportQuality": 0.8,
						"imageSpriteId": 7855226,
						"collisionPoly": {
							"points": [
								1,
								0,
								1,
								1,
								0,
								1,
								0,
								0
							]
						},
						"useCollisionPoly": true,
						"duration": 1
					},
					{
						"width": 102,
						"height": 112,
						"originX": 0.5,
						"originY": 0.5,
						"originalSource": "",
						"exportFormat": "lossless",
						"exportQuality": 0.8,
						"imageSpriteId": 3547735,
						"collisionPoly": {
							"points": [
								1,
								0,
								1,
								1,
								0,
								1,
								0,
								0
							]
						},
						"useCollisionPoly": true,
						"duration": 1
					},
					{
						"width": 102,
						"height": 112,
						"originX": 0.5,
						"originY": 0.5,
						"originalSource": "",
						"exportFormat": "lossless",
						"exportQuality": 0.8,
						"imageSpriteId": 9767562,
						"collisionPoly": {
							"points": [
								1,
								0,
								1,
								1,
								0,
								1,
								0,
								0
							]
						},
						"useCollisionPoly": true,
						"duration": 1
					},
					{
						"width": 102,
						"height": 112,
						"originX": 0.5,
						"originY": 0.5,
						"originalSource": "",
						"exportFormat": "lossless",
						"exportQuality": 0.8,
						"imageSpriteId": 6348378,
						"collisionPoly": {
							"points": [
								1,
								0,
								1,
								1,
								0,
								1,
								0,
								0
							]
						},
						"useCollisionPoly": true,
						"duration": 1
					},
					{
						"width": 102,
						"height": 112,
						"originX": 0.5,
						"originY": 0.5,
						"originalSource": "",
						"exportFormat": "lossless",
						"exportQuality": 0.8,
						"imageSpriteId": 4765257,
						"collisionPoly": {
							"points": [
								1,
								0,
								1,
								1,
								0,
								1,
								0,
								0
							]
						},
						"useCollisionPoly": true,
						"duration": 1
					}
				],
				"sid": 289328112590362,
				"name": "3",
				"isLooping": true,
				"isPingPong": false,
				"repeatCount": 1,
				"repeatTo": 0,
				"speed": 24
			}
		],
		"subfolders": []
	}
}