{
	"name": "ShipSelect",
	"layers": [
		{
			"name": "background",
			"overriden": 0,
			"subLayers": [],
			"instances": [],
			"sid": 775647393691667,
			"effectTypes": [],
			"isInitiallyVisible": true,
			"isInitiallyInteractive": true,
			"color": [
				1,
				1,
				1,
				1
			],
			"backgroundColor": [
				0.3686274509803922,
				0.3686274509803922,
				0.3686274509803922,
				1
			],
			"isTransparent": false,
			"parallaxX": 1,
			"parallaxY": 1,
			"scaleRate": 1,
			"forceOwnTexture": false,
			"renderingMode": "3d",
			"drawOrder": "z-order",
			"useRenderCells": false,
			"blendMode": "normal",
			"zElevation": 0,
			"global": false
		},
		{
			"name": "arena",
			"overriden": 0,
			"subLayers": [],
			"instances": [],
			"sid": 318805633601475,
			"effectTypes": [],
			"isInitiallyVisible": true,
			"isInitiallyInteractive": true,
			"color": [
				1,
				1,
				1,
				1
			],
			"backgroundColor": [
				0.3686274509803922,
				0.3686274509803922,
				0.3686274509803922,
				1
			],
			"isTransparent": true,
			"parallaxX": 1,
			"parallaxY": 1,
			"scaleRate": 1,
			"forceOwnTexture": false,
			"renderingMode": "3d",
			"drawOrder": "z-order",
			"useRenderCells": false,
			"blendMode": "normal",
			"zElevation": 0,
			"global": false
		},
		{
			"name": "shipGrid",
			"overriden": 0,
			"subLayers": [],
			"instances": [
				{
					"type": "Sprite",
					"properties": {
						"initially-visible": true,
						"initial-animation": "Animation 1",
						"initial-frame": 0,
						"enable-collisions": true,
						"live-preview": false
					},
					"uid": 9,
					"instanceVariables": {},
					"behaviors": {},
					"world": {
						"x": 1280,
						"y": 0,
						"width": 560,
						"height": 720,
						"originX": 1,
						"originY": 0,
						"color": [
							1,
							1,
							1,
							1
						],
						"angle": 0,
						"zElevation": 0
					}
				},
				{
					"type": "align",
					"properties": {
						"initially-visible": false,
						"initial-animation": "align",
						"initial-frame": 0,
						"enable-collisions": true,
						"live-preview": false
					},
					"uid": 24,
					"instanceVariables": {
						"State": "playerShip"
					},
					"behaviors": {},
					"world": {
						"x": 835,
						"y": 304,
						"width": 128,
						"height": 128,
						"originX": 0.5,
						"originY": 0.5,
						"color": [
							1,
							1,
							1,
							1
						],
						"angle": 0,
						"zElevation": 0
					}
				},
				{
					"type": "gridTitle",
					"properties": {
						"text": "Engineer Your Ship",
						"enable-bbcode": true,
						"font": "Retro Gaming",
						"size": 24,
						"line-height": 0,
						"bold": false,
						"italic": false,
						"color": [
							0.9372549019607843,
							0.6784313725490196,
							0.41568627450980394,
							1
						],
						"horizontal-alignment": "center",
						"vertical-alignment": "center",
						"wrapping": "word",
						"initially-visible": true,
						"origin": "center",
						"read-aloud": false
					},
					"uid": 25,
					"instanceVariables": {},
					"behaviors": {},
					"world": {
						"x": 996.5454545454548,
						"y": 38.49586776859505,
						"width": 458.67768595041343,
						"height": 42.39669421487605,
						"originX": 0.5,
						"originY": 0.5,
						"color": [
							1,
							1,
							1,
							1
						],
						"angle": 0,
						"zElevation": 0
					}
				},
				{
					"type": "engineerBay",
					"properties": {
						"initially-visible": true,
						"initial-animation": "engineerBay",
						"initial-frame": 0,
						"enable-collisions": true,
						"live-preview": false
					},
					"uid": 27,
					"instanceVariables": {},
					"behaviors": {},
					"world": {
						"x": 360,
						"y": 274,
						"width": 448,
						"height": 408,
						"originX": 0.5,
						"originY": 0.5,
						"color": [
							1,
							1,
							1,
							1
						],
						"angle": 0,
						"zElevation": 0
					}
				},
				{
					"type": "launchButton",
					"properties": {
						"initially-visible": true,
						"initial-animation": "button",
						"initial-frame": 0,
						"enable-collisions": true,
						"live-preview": false
					},
					"uid": 28,
					"instanceVariables": {},
					"behaviors": {},
					"world": {
						"x": 360,
						"y": 584,
						"width": 192,
						"height": 64,
						"originX": 0.5,
						"originY": 0.5,
						"color": [
							1,
							1,
							1,
							1
						],
						"angle": 0,
						"zElevation": 0
					}
				},
				{
					"type": "launchButtonText",
					"properties": {
						"text": "Launch",
						"enable-bbcode": true,
						"font": "advanced_pixel_lcd-7",
						"size": 14,
						"line-height": 0,
						"bold": false,
						"italic": false,
						"color": [
							0.21176470588235294,
							0.2823529411764706,
							0.30196078431372547,
							1
						],
						"horizontal-alignment": "center",
						"vertical-alignment": "bottom",
						"wrapping": "word",
						"initially-visible": true,
						"origin": "center",
						"read-aloud": false
					},
					"uid": 29,
					"instanceVariables": {},
					"behaviors": {},
					"world": {
						"x": 360,
						"y": 584,
						"width": 160,
						"height": 39.09090909090901,
						"originX": 0.5,
						"originY": 0.5,
						"color": [
							1,
							1,
							1,
							1
						],
						"angle": 0,
						"zElevation": 0
					}
				},
				{
					"type": "shipStats",
					"properties": {
						"initially-visible": true,
						"initial-animation": "shipStats",
						"initial-frame": 0,
						"enable-collisions": true,
						"live-preview": false
					},
					"uid": 30,
					"instanceVariables": {},
					"behaviors": {},
					"world": {
						"x": 1003,
						"y": 542,
						"width": 480,
						"height": 296,
						"originX": 0.5,
						"originY": 0.5,
						"color": [
							1,
							1,
							1,
							1
						],
						"angle": 0,
						"zElevation": 0
					}
				},
				{
					"type": "gridTitle",
					"properties": {
						"text": "Connect the parts to create your ship",
						"enable-bbcode": true,
						"font": "Retro Gaming",
						"size": 14,
						"line-height": 0,
						"bold": false,
						"italic": false,
						"color": [
							0.9372549019607843,
							0.6784313725490196,
							0.41568627450980394,
							1
						],
						"horizontal-alignment": "center",
						"vertical-alignment": "center",
						"wrapping": "word",
						"initially-visible": true,
						"origin": "center",
						"read-aloud": false
					},
					"uid": 26,
					"instanceVariables": {},
					"behaviors": {},
					"world": {
						"x": 994.8925619834714,
						"y": 87.0495867768595,
						"width": 361.1570247933887,
						"height": 50.93795553545675,
						"originX": 0.5,
						"originY": 0.5,
						"color": [
							1,
							1,
							1,
							1
						],
						"angle": 0,
						"zElevation": 0
					}
				},
				{
					"type": "tab",
					"properties": {
						"initially-visible": true,
						"initial-animation": "tab",
						"initial-frame": 1,
						"enable-collisions": true,
						"live-preview": false
					},
					"uid": 31,
					"instanceVariables": {
						"thisTab": "core"
					},
					"behaviors": {},
					"world": {
						"x": 827,
						"y": 184,
						"width": 128,
						"height": 64,
						"originX": 0.5,
						"originY": 0.5,
						"color": [
							1,
							1,
							1,
							1
						],
						"angle": 0,
						"zElevation": 0
					}
				},
				{
					"type": "tab",
					"properties": {
						"initially-visible": true,
						"initial-animation": "tab",
						"initial-frame": 0,
						"enable-collisions": true,
						"live-preview": false
					},
					"uid": 32,
					"instanceVariables": {
						"thisTab": "weapon"
					},
					"behaviors": {},
					"world": {
						"x": 1003,
						"y": 184,
						"width": 128,
						"height": 64,
						"originX": 0.5,
						"originY": 0.5,
						"color": [
							1,
							1,
							1,
							1
						],
						"angle": 0,
						"zElevation": 0
					}
				},
				{
					"type": "tab",
					"properties": {
						"initially-visible": true,
						"initial-animation": "tab",
						"initial-frame": 0,
						"enable-collisions": true,
						"live-preview": false
					},
					"uid": 33,
					"instanceVariables": {
						"thisTab": "engine"
					},
					"behaviors": {},
					"world": {
						"x": 1179,
						"y": 184,
						"width": 128,
						"height": 64,
						"originX": 0.5,
						"originY": 0.5,
						"color": [
							1,
							1,
							1,
							1
						],
						"angle": 0,
						"zElevation": 0
					}
				},
				{
					"type": "tabTitle",
					"properties": {
						"text": "Core",
						"enable-bbcode": true,
						"font": "Retro Gaming",
						"size": 16,
						"line-height": 0,
						"bold": false,
						"italic": false,
						"color": [
							0.9372549019607843,
							0.6784313725490196,
							0.41568627450980394,
							1
						],
						"horizontal-alignment": "center",
						"vertical-alignment": "center",
						"wrapping": "word",
						"initially-visible": true,
						"origin": "center",
						"read-aloud": false
					},
					"uid": 34,
					"instanceVariables": {},
					"behaviors": {},
					"world": {
						"x": 827,
						"y": 184,
						"width": 114,
						"height": 30,
						"originX": 0.5,
						"originY": 0.5,
						"color": [
							1,
							1,
							1,
							1
						],
						"angle": 0,
						"zElevation": 0
					}
				},
				{
					"type": "tabTitle",
					"properties": {
						"text": "Weapon",
						"enable-bbcode": true,
						"font": "Retro Gaming",
						"size": 16,
						"line-height": 0,
						"bold": false,
						"italic": false,
						"color": [
							0.9372549019607843,
							0.6784313725490196,
							0.41568627450980394,
							1
						],
						"horizontal-alignment": "center",
						"vertical-alignment": "center",
						"wrapping": "word",
						"initially-visible": true,
						"origin": "center",
						"read-aloud": false
					},
					"uid": 35,
					"instanceVariables": {},
					"behaviors": {},
					"world": {
						"x": 1003,
						"y": 184,
						"width": 114,
						"height": 30,
						"originX": 0.5,
						"originY": 0.5,
						"color": [
							1,
							1,
							1,
							1
						],
						"angle": 0,
						"zElevation": 0
					}
				},
				{
					"type": "tabTitle",
					"properties": {
						"text": "Engine",
						"enable-bbcode": true,
						"font": "Retro Gaming",
						"size": 16,
						"line-height": 0,
						"bold": false,
						"italic": false,
						"color": [
							0.9372549019607843,
							0.6784313725490196,
							0.41568627450980394,
							1
						],
						"horizontal-alignment": "center",
						"vertical-alignment": "center",
						"wrapping": "word",
						"initially-visible": true,
						"origin": "center",
						"read-aloud": false
					},
					"uid": 36,
					"instanceVariables": {},
					"behaviors": {},
					"world": {
						"x": 1179,
						"y": 184,
						"width": 114,
						"height": 30,
						"originX": 0.5,
						"originY": 0.5,
						"color": [
							1,
							1,
							1,
							1
						],
						"angle": 0,
						"zElevation": 0
					}
				},
				{
					"type": "alignShip",
					"properties": {
						"initially-visible": false,
						"initial-animation": "align",
						"initial-frame": 0,
						"enable-collisions": true,
						"live-preview": false
					},
					"uid": 37,
					"instanceVariables": {
						"State": "bay"
					},
					"behaviors": {},
					"world": {
						"x": 360,
						"y": 298,
						"width": 128,
						"height": 128,
						"originX": 0.5,
						"originY": 0.5,
						"color": [
							1,
							1,
							1,
							1
						],
						"angle": 0,
						"zElevation": 0
					}
				},
				{
					"type": "coreStatText",
					"properties": {
						"text": "HP",
						"enable-bbcode": true,
						"font": "Retro Gaming",
						"size": 16,
						"line-height": 0,
						"bold": false,
						"italic": false,
						"color": [
							0.9372549019607843,
							0.6784313725490196,
							0.41568627450980394,
							1
						],
						"horizontal-alignment": "left",
						"vertical-alignment": "top",
						"wrapping": "word",
						"initially-visible": true,
						"origin": "top-left",
						"read-aloud": false
					},
					"uid": 38,
					"instanceVariables": {},
					"behaviors": {},
					"world": {
						"x": 806.0495867768593,
						"y": 406.0330578512398,
						"width": 114,
						"height": 30,
						"originX": 0,
						"originY": 0,
						"color": [
							1,
							1,
							1,
							1
						],
						"angle": 0,
						"zElevation": 0
					}
				},
				{
					"type": "coreStatText",
					"properties": {
						"text": "Shields",
						"enable-bbcode": true,
						"font": "Retro Gaming",
						"size": 16,
						"line-height": 0,
						"bold": false,
						"italic": false,
						"color": [
							0.9372549019607843,
							0.6784313725490196,
							0.41568627450980394,
							1
						],
						"horizontal-alignment": "left",
						"vertical-alignment": "top",
						"wrapping": "word",
						"initially-visible": true,
						"origin": "top-left",
						"read-aloud": false
					},
					"uid": 40,
					"instanceVariables": {},
					"behaviors": {},
					"world": {
						"x": 949.0495867768594,
						"y": 406.0330578512398,
						"width": 114,
						"height": 30,
						"originX": 0,
						"originY": 0,
						"color": [
							1,
							1,
							1,
							1
						],
						"angle": 0,
						"zElevation": 0
					}
				},
				{
					"type": "coreStatText",
					"properties": {
						"text": "Regen",
						"enable-bbcode": true,
						"font": "Retro Gaming",
						"size": 16,
						"line-height": 0,
						"bold": false,
						"italic": false,
						"color": [
							0.9372549019607843,
							0.6784313725490196,
							0.41568627450980394,
							1
						],
						"horizontal-alignment": "left",
						"vertical-alignment": "top",
						"wrapping": "word",
						"initially-visible": true,
						"origin": "top-left",
						"read-aloud": false
					},
					"uid": 42,
					"instanceVariables": {},
					"behaviors": {},
					"world": {
						"x": 1092.0495867768595,
						"y": 406.0330578512398,
						"width": 114,
						"height": 30,
						"originX": 0,
						"originY": 0,
						"color": [
							1,
							1,
							1,
							1
						],
						"angle": 0,
						"zElevation": 0
					}
				},
				{
					"type": "indicatorBarFill",
					"properties": {
						"initially-visible": true,
						"initial-animation": "indicatorBarFill",
						"initial-frame": 0,
						"enable-collisions": true,
						"live-preview": false
					},
					"uid": 44,
					"instanceVariables": {
						"State": "hp"
					},
					"behaviors": {},
					"world": {
						"x": 800.1652892561987,
						"y": 453.03305785123985,
						"width": 1,
						"height": 32,
						"originX": 0.03125,
						"originY": 0.5,
						"color": [
							1,
							1,
							1,
							1
						],
						"angle": 0,
						"zElevation": 0
					}
				},
				{
					"type": "indicatorBarFill",
					"properties": {
						"initially-visible": true,
						"initial-animation": "indicatorBarFill",
						"initial-frame": 0,
						"enable-collisions": true,
						"live-preview": false
					},
					"uid": 45,
					"instanceVariables": {
						"State": "shields"
					},
					"behaviors": {},
					"world": {
						"x": 943.1652892561987,
						"y": 453.03305785123985,
						"width": 1,
						"height": 32,
						"originX": 0.03125,
						"originY": 0.5,
						"color": [
							1,
							1,
							1,
							1
						],
						"angle": 0,
						"zElevation": 0
					}
				},
				{
					"type": "indicatorBarFill",
					"properties": {
						"initially-visible": true,
						"initial-animation": "indicatorBarFill",
						"initial-frame": 0,
						"enable-collisions": true,
						"live-preview": false
					},
					"uid": 46,
					"instanceVariables": {
						"State": "generator"
					},
					"behaviors": {},
					"world": {
						"x": 1086.1652892561988,
						"y": 453.03305785123985,
						"width": 1,
						"height": 32,
						"originX": 0.03125,
						"originY": 0.5,
						"color": [
							1,
							1,
							1,
							1
						],
						"angle": 0,
						"zElevation": 0
					}
				},
				{
					"type": "coreStatText",
					"properties": {
						"text": "Rate",
						"enable-bbcode": true,
						"font": "Retro Gaming",
						"size": 16,
						"line-height": 0,
						"bold": false,
						"italic": false,
						"color": [
							0.9372549019607843,
							0.6784313725490196,
							0.41568627450980394,
							1
						],
						"horizontal-alignment": "left",
						"vertical-alignment": "top",
						"wrapping": "word",
						"initially-visible": true,
						"origin": "top-left",
						"read-aloud": false
					},
					"uid": 47,
					"instanceVariables": {},
					"behaviors": {},
					"world": {
						"x": 806.876033057851,
						"y": 505.44628099173576,
						"width": 114,
						"height": 30,
						"originX": 0,
						"originY": 0,
						"color": [
							1,
							1,
							1,
							1
						],
						"angle": 0,
						"zElevation": 0
					}
				},
				{
					"type": "coreStatText",
					"properties": {
						"text": "Speed",
						"enable-bbcode": true,
						"font": "Retro Gaming",
						"size": 16,
						"line-height": 0,
						"bold": false,
						"italic": false,
						"color": [
							0.9372549019607843,
							0.6784313725490196,
							0.41568627450980394,
							1
						],
						"horizontal-alignment": "left",
						"vertical-alignment": "top",
						"wrapping": "word",
						"initially-visible": true,
						"origin": "top-left",
						"read-aloud": false
					},
					"uid": 48,
					"instanceVariables": {},
					"behaviors": {},
					"world": {
						"x": 949.876033057851,
						"y": 505.44628099173576,
						"width": 114,
						"height": 30,
						"originX": 0,
						"originY": 0,
						"color": [
							1,
							1,
							1,
							1
						],
						"angle": 0,
						"zElevation": 0
					}
				},
				{
					"type": "coreStatText",
					"properties": {
						"text": "Damage",
						"enable-bbcode": true,
						"font": "Retro Gaming",
						"size": 16,
						"line-height": 0,
						"bold": false,
						"italic": false,
						"color": [
							0.9372549019607843,
							0.6784313725490196,
							0.41568627450980394,
							1
						],
						"horizontal-alignment": "left",
						"vertical-alignment": "top",
						"wrapping": "word",
						"initially-visible": true,
						"origin": "top-left",
						"read-aloud": false
					},
					"uid": 49,
					"instanceVariables": {},
					"behaviors": {},
					"world": {
						"x": 1092.8760330578511,
						"y": 505.44628099173576,
						"width": 114,
						"height": 30,
						"originX": 0,
						"originY": 0,
						"color": [
							1,
							1,
							1,
							1
						],
						"angle": 0,
						"zElevation": 0
					}
				},
				{
					"type": "indicatorBarFill",
					"properties": {
						"initially-visible": true,
						"initial-animation": "indicatorBarFill",
						"initial-frame": 0,
						"enable-collisions": true,
						"live-preview": false
					},
					"uid": 50,
					"instanceVariables": {
						"State": "fireRate"
					},
					"behaviors": {},
					"world": {
						"x": 800.1652892561987,
						"y": 552.0330578512398,
						"width": 1,
						"height": 32,
						"originX": 0.03125,
						"originY": 0.5,
						"color": [
							1,
							1,
							1,
							1
						],
						"angle": 0,
						"zElevation": 0
					}
				},
				{
					"type": "indicatorBarFill",
					"properties": {
						"initially-visible": true,
						"initial-animation": "indicatorBarFill",
						"initial-frame": 0,
						"enable-collisions": true,
						"live-preview": false
					},
					"uid": 51,
					"instanceVariables": {
						"State": "bulletSpeed"
					},
					"behaviors": {},
					"world": {
						"x": 943.1652892561987,
						"y": 552.0330578512398,
						"width": 1,
						"height": 32,
						"originX": 0.03125,
						"originY": 0.5,
						"color": [
							1,
							1,
							1,
							1
						],
						"angle": 0,
						"zElevation": 0
					}
				},
				{
					"type": "indicatorBarFill",
					"properties": {
						"initially-visible": true,
						"initial-animation": "indicatorBarFill",
						"initial-frame": 0,
						"enable-collisions": true,
						"live-preview": false
					},
					"uid": 52,
					"instanceVariables": {
						"State": "bulletDamage"
					},
					"behaviors": {},
					"world": {
						"x": 1086.1652892561988,
						"y": 552.0330578512398,
						"width": 1,
						"height": 32,
						"originX": 0.03125,
						"originY": 0.5,
						"color": [
							1,
							1,
							1,
							1
						],
						"angle": 0,
						"zElevation": 0
					}
				},
				{
					"type": "coreStatText",
					"properties": {
						"text": "Accel",
						"enable-bbcode": true,
						"font": "Retro Gaming",
						"size": 16,
						"line-height": 0,
						"bold": false,
						"italic": false,
						"color": [
							0.9372549019607843,
							0.6784313725490196,
							0.41568627450980394,
							1
						],
						"horizontal-alignment": "left",
						"vertical-alignment": "top",
						"wrapping": "word",
						"initially-visible": true,
						"origin": "top-left",
						"read-aloud": false
					},
					"uid": 56,
					"instanceVariables": {},
					"behaviors": {},
					"world": {
						"x": 807.702479338843,
						"y": 601.2066115702482,
						"width": 114,
						"height": 30,
						"originX": 0,
						"originY": 0,
						"color": [
							1,
							1,
							1,
							1
						],
						"angle": 0,
						"zElevation": 0
					}
				},
				{
					"type": "coreStatText",
					"properties": {
						"text": "Agility",
						"enable-bbcode": true,
						"font": "Retro Gaming",
						"size": 16,
						"line-height": 0,
						"bold": false,
						"italic": false,
						"color": [
							0.9372549019607843,
							0.6784313725490196,
							0.41568627450980394,
							1
						],
						"horizontal-alignment": "left",
						"vertical-alignment": "top",
						"wrapping": "word",
						"initially-visible": true,
						"origin": "top-left",
						"read-aloud": false
					},
					"uid": 57,
					"instanceVariables": {},
					"behaviors": {},
					"world": {
						"x": 950.702479338843,
						"y": 601.2066115702482,
						"width": 114,
						"height": 30,
						"originX": 0,
						"originY": 0,
						"color": [
							1,
							1,
							1,
							1
						],
						"angle": 0,
						"zElevation": 0
					}
				},
				{
					"type": "indicatorBarFill",
					"properties": {
						"initially-visible": true,
						"initial-animation": "indicatorBarFill",
						"initial-frame": 0,
						"enable-collisions": true,
						"live-preview": false
					},
					"uid": 58,
					"instanceVariables": {
						"State": "acceleration"
					},
					"behaviors": {},
					"world": {
						"x": 800.1652892561987,
						"y": 649.0330578512398,
						"width": 1,
						"height": 32,
						"originX": 0.03125,
						"originY": 0.5,
						"color": [
							1,
							1,
							1,
							1
						],
						"angle": 0,
						"zElevation": 0
					}
				},
				{
					"type": "indicatorBarFill",
					"properties": {
						"initially-visible": true,
						"initial-animation": "indicatorBarFill",
						"initial-frame": 0,
						"enable-collisions": true,
						"live-preview": false
					},
					"uid": 59,
					"instanceVariables": {
						"State": "turnSpeed"
					},
					"behaviors": {},
					"world": {
						"x": 943.1652892561987,
						"y": 649.0330578512398,
						"width": 1,
						"height": 32,
						"originX": 0.03125,
						"originY": 0.5,
						"color": [
							1,
							1,
							1,
							1
						],
						"angle": 0,
						"zElevation": 0
					}
				},
				{
					"type": "indicatorBar",
					"properties": {
						"initially-visible": true,
						"initial-animation": "indicatorBar",
						"initial-frame": 0,
						"enable-collisions": true,
						"live-preview": false
					},
					"uid": 39,
					"instanceVariables": {},
					"behaviors": {},
					"world": {
						"x": 798.1652892561987,
						"y": 453.03305785123985,
						"width": 128,
						"height": 32,
						"originX": 0,
						"originY": 0.5,
						"color": [
							1,
							1,
							1,
							1
						],
						"angle": 0,
						"zElevation": 1
					}
				},
				{
					"type": "indicatorBar",
					"properties": {
						"initially-visible": true,
						"initial-animation": "indicatorBar",
						"initial-frame": 0,
						"enable-collisions": true,
						"live-preview": false
					},
					"uid": 41,
					"instanceVariables": {},
					"behaviors": {},
					"world": {
						"x": 941.1652892561987,
						"y": 453.03305785123985,
						"width": 128,
						"height": 32,
						"originX": 0,
						"originY": 0.5,
						"color": [
							1,
							1,
							1,
							1
						],
						"angle": 0,
						"zElevation": 1
					}
				},
				{
					"type": "indicatorBar",
					"properties": {
						"initially-visible": true,
						"initial-animation": "indicatorBar",
						"initial-frame": 0,
						"enable-collisions": true,
						"live-preview": false
					},
					"uid": 43,
					"instanceVariables": {},
					"behaviors": {},
					"world": {
						"x": 1084.1652892561988,
						"y": 453.03305785123985,
						"width": 128,
						"height": 32,
						"originX": 0,
						"originY": 0.5,
						"color": [
							1,
							1,
							1,
							1
						],
						"angle": 0,
						"zElevation": 1
					}
				},
				{
					"type": "indicatorBar",
					"properties": {
						"initially-visible": true,
						"initial-animation": "indicatorBar",
						"initial-frame": 0,
						"enable-collisions": true,
						"live-preview": false
					},
					"uid": 53,
					"instanceVariables": {},
					"behaviors": {},
					"world": {
						"x": 798.1652892561987,
						"y": 552.0330578512398,
						"width": 128,
						"height": 32,
						"originX": 0,
						"originY": 0.5,
						"color": [
							1,
							1,
							1,
							1
						],
						"angle": 0,
						"zElevation": 1
					}
				},
				{
					"type": "indicatorBar",
					"properties": {
						"initially-visible": true,
						"initial-animation": "indicatorBar",
						"initial-frame": 0,
						"enable-collisions": true,
						"live-preview": false
					},
					"uid": 54,
					"instanceVariables": {},
					"behaviors": {},
					"world": {
						"x": 941.1652892561987,
						"y": 552.0330578512398,
						"width": 128,
						"height": 32,
						"originX": 0,
						"originY": 0.5,
						"color": [
							1,
							1,
							1,
							1
						],
						"angle": 0,
						"zElevation": 1
					}
				},
				{
					"type": "indicatorBar",
					"properties": {
						"initially-visible": true,
						"initial-animation": "indicatorBar",
						"initial-frame": 0,
						"enable-collisions": true,
						"live-preview": false
					},
					"uid": 55,
					"instanceVariables": {},
					"behaviors": {},
					"world": {
						"x": 1084.1652892561988,
						"y": 552.0330578512398,
						"width": 128,
						"height": 32,
						"originX": 0,
						"originY": 0.5,
						"color": [
							1,
							1,
							1,
							1
						],
						"angle": 0,
						"zElevation": 1
					}
				},
				{
					"type": "indicatorBar",
					"properties": {
						"initially-visible": true,
						"initial-animation": "indicatorBar",
						"initial-frame": 0,
						"enable-collisions": true,
						"live-preview": false
					},
					"uid": 60,
					"instanceVariables": {},
					"behaviors": {},
					"world": {
						"x": 798.1652892561987,
						"y": 649.0330578512398,
						"width": 128,
						"height": 32,
						"originX": 0,
						"originY": 0.5,
						"color": [
							1,
							1,
							1,
							1
						],
						"angle": 0,
						"zElevation": 1
					}
				},
				{
					"type": "indicatorBar",
					"properties": {
						"initially-visible": true,
						"initial-animation": "indicatorBar",
						"initial-frame": 0,
						"enable-collisions": true,
						"live-preview": false
					},
					"uid": 61,
					"instanceVariables": {},
					"behaviors": {},
					"world": {
						"x": 941.1652892561987,
						"y": 649.0330578512398,
						"width": 128,
						"height": 32,
						"originX": 0,
						"originY": 0.5,
						"color": [
							1,
							1,
							1,
							1
						],
						"angle": 0,
						"zElevation": 1
					}
				}
			],
			"sid": 415253029311991,
			"effectTypes": [],
			"isInitiallyVisible": true,
			"isInitiallyInteractive": true,
			"color": [
				1,
				1,
				1,
				1
			],
			"backgroundColor": [
				0.3686274509803922,
				0.3686274509803922,
				0.3686274509803922,
				1
			],
			"isTransparent": true,
			"parallaxX": 1,
			"parallaxY": 1,
			"scaleRate": 1,
			"forceOwnTexture": false,
			"renderingMode": "3d",
			"drawOrder": "z-order",
			"useRenderCells": false,
			"blendMode": "normal",
			"zElevation": 0,
			"global": true
		}
	],
	"sid": 639517992028147,
	"nonworld-instances": [],
	"effectTypes": [],
	"width": 1280,
	"height": 720,
	"unboundedScrolling": true,
	"vpX": 0.5,
	"vpY": 0.5,
	"projection": "orthographic",
	"eventSheet": "ShipSelectES"
}